dj_cqrs/__init__.py
dj_cqrs/_validation.py
dj_cqrs/admin.py
dj_cqrs/apps.py
dj_cqrs/constants.py
dj_cqrs/controller/__init__.py
dj_cqrs/controller/consumer.py
dj_cqrs/controller/producer.py
dj_cqrs/correlation.py
dj_cqrs/dataclasses.py
dj_cqrs/delay.py
dj_cqrs/logger.py
dj_cqrs/management/__init__.py
dj_cqrs/management/commands/__init__.py
dj_cqrs/management/commands/cqrs_bulk_dump.py
dj_cqrs/management/commands/cqrs_bulk_load.py
dj_cqrs/management/commands/cqrs_consume.py
dj_cqrs/management/commands/cqrs_dead_letters.py
dj_cqrs/management/commands/cqrs_deleted_diff_master.py
dj_cqrs/management/commands/cqrs_deleted_diff_replica.py
dj_cqrs/management/commands/cqrs_deleted_sync_replica.py
dj_cqrs/management/commands/cqrs_diff_master.py
dj_cqrs/management/commands/cqrs_diff_replica.py
dj_cqrs/management/commands/cqrs_diff_sync.py
dj_cqrs/management/commands/cqrs_sync.py
dj_cqrs/management/utils.py
dj_cqrs/managers.py
dj_cqrs/metas.py
dj_cqrs/mixins.py
dj_cqrs/registries.py
dj_cqrs/signals.py
dj_cqrs/state.py
dj_cqrs/tracker.py
dj_cqrs/transport/__init__.py
dj_cqrs/transport/base.py
dj_cqrs/transport/kombu.py
dj_cqrs/transport/mixins.py
dj_cqrs/transport/mock.py
dj_cqrs/transport/rabbit_mq.py
dj_cqrs/utils.py
django_cqrs-2.8.1.dist-info/LICENSE
django_cqrs-2.8.1.dist-info/METADATA
django_cqrs-2.8.1.dist-info/WHEEL
django_cqrs-2.8.1.dist-info/RECORD
