Metadata-Version: 2.1
Name: django-cqrs
Version: 2.8.1
Summary: Django CQRS data synchronisation
Home-page: https://django-cqrs.readthedocs.org
License: Apache-2.0
Keywords: django,cqrs,sql,mixin,amqp
Author: CloudBlue LLC
Requires-Python: >=3.8,<4
Classifier: Development Status :: 5 - Production/Stable
Classifier: Framework :: Django :: 3.2
Classifier: Framework :: Django :: 4.0
Classifier: Framework :: Django :: 4.1
Classifier: Framework :: Django :: 4.2
Classifier: Intended Audience :: Developers
Classifier: License :: OSI Approved :: Apache Software License
Classifier: Operating System :: Unix
Classifier: Programming Language :: Python :: 3
Classifier: Programming Language :: Python :: 3.8
Classifier: Programming Language :: Python :: 3.9
Classifier: Programming Language :: Python :: 3.10
Classifier: Programming Language :: Python :: 3.11
Classifier: Programming Language :: Python :: 3.12
Classifier: Programming Language :: Python :: 3.13
Classifier: Topic :: Communications
Classifier: Topic :: Database
Requires-Dist: django (>=3.2)
Requires-Dist: django-model-utils (>=4.0.0,<4.5)
Requires-Dist: kombu (>=4.6)
Requires-Dist: pika (>=1.0.0)
Requires-Dist: python-dateutil (>=2.4)
Requires-Dist: ujson (>=5.4.0)
Requires-Dist: watchfiles (>=0.18.1,<0.19.0)
Project-URL: Repository, https://github.com/cloudblue/django-cqrs
